[
  {
    "grupo": "836",
    "classe": "'-7",
    "codigo": "892",
    "descricao": "PROPAGANDA E PUBLICIDADE"
  },
  {
    "grupo": "836",
    "classe": "'-7",
    "codigo": "4227",
    "descricao": "PUBLICACOES PROMOCIONAIS / EDITAIS"
  },
  {
    "grupo": "836",
    "classe": "'-7",
    "codigo": "10200",
    "descricao": "PRODUCAO JORNALISTICA"
  },
  {
    "grupo": "836",
    "classe": "'-7",
    "codigo": "14974",
    "descricao": "DIVULGACAO TECNICO-CIENTIFICA"
  },
  {
    "grupo": "836",
    "classe": "'-7",
    "codigo": "16152",
    "descricao": "PUBLICACAO LIVRO / MATERIA - PERIODICA / OFICIAL"
  },
  {
    "grupo": "836",
    "classe": "'-7",
    "codigo": "24988",
    "descricao": "SERVICOS DE SUPORTE DE DIVULGACAO EM COMUNICACAO SOCIAL"
  },
  {
    "grupo": "836",
    "classe": "8369",
    "codigo": "21709",
    "descricao": "CONFECCAO IMPRESSAO TAMPOGRAFICA"
  }
]