[
  {
    "grupo": "969",
    "classe": "'-7",
    "codigo": "12955",
    "descricao": "LOCUCAO DE TEXTO / MESTRE DE CERIMONIA / LOCUTOR /  APRESEN-TADOR"
  },
  {
    "grupo": "969",
    "classe": "'-7",
    "codigo": "15288",
    "descricao": "CENOGRAFIA"
  },
  {
    "grupo": "969",
    "classe": "'-7",
    "codigo": "17019",
    "descricao": "DECORACAO - EVENTOS / SOLENIDADES"
  },
  {
    "grupo": "969",
    "classe": "'-7",
    "codigo": "19933",
    "descricao": "INTERCAMBIO CULTURAL"
  },
  {
    "grupo": "969",
    "classe": "'-7",
    "codigo": "24376",
    "descricao": "INSTALACAO E MONTAGEM DE PALCO"
  },
  {
    "grupo": "969",
    "classe": "9691",
    "codigo": "19640",
    "descricao": "INGRESSO - PARQUE / EVENTOS"
  },
  {
    "grupo": "969",
    "classe": "9699",
    "codigo": "16721",
    "descricao": "JOGO / DIVERSAO ELETRONICA"
  }
]